{
    "_links": {
        "self": {
            "href": "http:\/\/default\/admin\/structure\/menu\/item\/9\/edit?_format=hal_json"
        },
        "type": {
            "href": "http:\/\/drupal.org\/rest\/type\/menu_link_content\/menu_link_content"
        },
        "http:\/\/drupal.org\/rest\/relation\/menu_link_content\/menu_link_content\/menu_link_content_parent_entity": [
            {
                "href": "http:\/\/default\/admin\/structure\/menu\/item\/7\/edit?_format=hal_json"
            }
        ]
    },
    "id": [
        {
            "value": 9
        }
    ],
    "uuid": [
        {
            "value": "8534c7f9-add3-4a59-b5d8-17e1f5339233"
        }
    ],
    "revision_id": [
        {
            "value": 46
        }
    ],
    "langcode": [
        {
            "value": "en",
            "lang": "en"
        }
    ],
    "bundle": [
        {
            "value": "menu_link_content"
        }
    ],
    "revision_created": [
        {
            "value": "2019-12-15T21:30:46+00:00",
            "format": "Y-m-d\\TH:i:sP"
        }
    ],
    "enabled": [
        {
            "value": true
        }
    ],
    "title": [
        {
            "value": "Layout 3",
            "lang": "en"
        }
    ],
    "menu_name": [
        {
            "value": "main"
        }
    ],
    "link": [
        {
            "uri": "internal:\/node\/6",
            "title": "",
            "options": []
        }
    ],
    "external": [
        {
            "value": false
        }
    ],
    "rediscover": [
        {
            "value": true
        }
    ],
    "weight": [
        {
            "value": -47
        }
    ],
    "expanded": [
        {
            "value": false
        }
    ],
    "parent": [
        {
            "value": "menu_link_content:c2a17c04-49f3-42c8-90fc-8098d9c04281"
        }
    ],
    "changed": [
        {
            "value": "2020-01-04T08:03:36+00:00",
            "lang": "en",
            "format": "Y-m-d\\TH:i:sP"
        }
    ],
    "default_langcode": [
        {
            "value": true,
            "lang": "en"
        }
    ],
    "revision_translation_affected": [
        {
            "value": true,
            "lang": "en"
        }
    ],
    "metatag": [
        {
            "value": {
                "title": "Combo 6 | EM Magazine",
                "canonical_url": "http:\/\/default\/combo\/6",
                "robots": "index, follow"
            }
        }
    ],
    "_embedded": {
        "http:\/\/drupal.org\/rest\/relation\/menu_link_content\/menu_link_content\/menu_link_content_parent_entity": [
            {
                "_links": {
                    "self": {
                        "href": "http:\/\/default\/admin\/structure\/menu\/item\/7\/edit?_format=hal_json"
                    },
                    "type": {
                        "href": "http:\/\/drupal.org\/rest\/type\/menu_link_content\/menu_link_content"
                    }
                },
                "uuid": [
                    {
                        "value": "c2a17c04-49f3-42c8-90fc-8098d9c04281"
                    }
                ]
            }
        ]
    }
}